stpl/__init__.py
stpl/stpl.py
stpl-1.13.6.data/data/share/man/man1/stpl.1
stpl-1.13.6.dist-info/LICENSE
stpl-1.13.6.dist-info/METADATA
stpl-1.13.6.dist-info/WHEEL
stpl-1.13.6.dist-info/entry_points.txt
stpl-1.13.6.dist-info/top_level.txt
stpl-1.13.6.dist-info/RECORD
