Metadata-Version: 2.1
Name: stpl
Version: 1.13.6
Summary: stpl - expand bottle SimpleTemplate
Home-page: https://github.com/rpuntaie/stpl
Author: Roland Puntaier
Author-email: roland.puntaier@gmail.com
License: MIT
Keywords: Duplicate, File
Platform: UNKNOWN
Classifier: Development Status :: 5 - Production/Stable
Classifier: Environment :: Console
Classifier: License :: OSI Approved :: MIT License
Classifier: Natural Language :: English
Classifier: Operating System :: OS Independent
Classifier: Operating System :: POSIX
Classifier: Programming Language :: Python
Classifier: Intended Audience :: End Users/Desktop
Classifier: Intended Audience :: Information Technology
Classifier: Topic :: Utilities
Provides-Extra: develop
Requires-Dist: mock ; extra == 'develop'
Requires-Dist: pytest ; extra == 'develop'
Requires-Dist: pytest-coverage ; extra == 'develop'
